mir_submit_batch/__init__.py
mir_submit_batch/submit_batch.py
mir_batch_tracking-0.0.3.dist-info/METADATA
mir_batch_tracking-0.0.3.dist-info/WHEEL
mir_batch_tracking-0.0.3.dist-info/entry_points.txt
mir_batch_tracking-0.0.3.dist-info/top_level.txt
mir_batch_tracking-0.0.3.dist-info/RECORD
